pypandoc_hwpx/PandocToHtml.py
pypandoc_hwpx/PandocToHwpx.py
pypandoc_hwpx/__init__.py
pypandoc_hwpx/blank.hwpx
pypandoc_hwpx/cli.py
pypandoc_hwpx-0.1.1.dist-info/licenses/LICENSE
pypandoc_hwpx-0.1.1.dist-info/METADATA
pypandoc_hwpx-0.1.1.dist-info/WHEEL
pypandoc_hwpx-0.1.1.dist-info/entry_points.txt
pypandoc_hwpx-0.1.1.dist-info/top_level.txt
pypandoc_hwpx-0.1.1.dist-info/RECORD
