Metadata-Version: 2.4
Name: pypandoc-hwpx
Version: 0.1.1
Summary: Convert Markdown/DOCX to HWPX using Pandoc AST
Home-page: https://github.com/msjang/pypandoc-hwpx
Author: pypandoc-hwpx Contributors
License: MIT
Project-URL: Source, https://github.com/msjang/pypandoc-hwpx
Project-URL: Tracker, https://github.com/msjang/pypandoc-hwpx/issues
Classifier: Programming Language :: Python :: 3
Classifier: License :: OSI Approved :: MIT License
Classifier: Operating System :: OS Independent
Requires-Python: >=3.6
License-File: LICENSE
Requires-Dist: pypandoc
Requires-Dist: Pillow
Dynamic: author
Dynamic: classifier
Dynamic: description
Dynamic: description-content-type
Dynamic: home-page
Dynamic: license
Dynamic: license-file
Dynamic: project-url
Dynamic: requires-dist
Dynamic: requires-python
Dynamic: summary
